discord/ext/bot/__init__.py
discord_ext_bot-1.0.1.dist-info/LICENSE.txt
discord_ext_bot-1.0.1.dist-info/METADATA
discord_ext_bot-1.0.1.dist-info/WHEEL
discord_ext_bot-1.0.1.dist-info/top_level.txt
discord_ext_bot-1.0.1.dist-info/RECORD
