Metadata-Version: 2.1
Name: discord-ext-bot
Version: 1.0.1
Summary: An package for discord.py.
Home-page: https://github.com/FrostiiWeeb/discord-ext-bot
Author: Alex Hutz
Author-email: frostiiflames@gmail.com
License: MIT
Platform: UNKNOWN
Requires-Python: >=3.8.1
